backpipe/__init__.py
backpipe/__main__.py
backpipe/app.py
backpipe/builder.py
backpipe/config.py
backpipe/defaults.py
backpipe/host.py
backpipe/redirect.py
backpipe/rq.py
backpipe/server.py
backpipe/uptime.py
backpipe/presets/__init__.py
backpipe/presets/file.py
backpipe/presets/ipaddr.py
backpipe/presets/redirect.py
backpipe/tools/__init__.py
backpipe/tools/check_type.py
backpipe/tools/base64/__init__.py
backpipe/tools/base64/decode.py
backpipe/tools/base64/encode.py
backpipe/tools/file/__init__.py
backpipe/tools/file/append.py
backpipe/tools/file/create.py
backpipe/tools/file/delete.py
backpipe/tools/file/write.py
backpipe/tools/hash/__init__.py
backpipe/tools/hash/md5.py
backpipe/tools/hash/sha1.py
backpipe/tools/hash/sha224.py
backpipe/tools/hash/sha256.py
backpipe/tools/hash/sha384.py
backpipe/tools/hash/sha512.py
backpipe/tools/html/__init__.py
backpipe/tools/html/addMeta.py
backpipe/tools/html/addStyle.py
backpipe/tools/html/addTag.py
backpipe/tools/html/html.py
backpipe/tools/json/__init__.py
backpipe/tools/json/deserialize.py
backpipe/tools/json/serialize.py
backpipe-0.6.5.dist-info/LICENSE
backpipe-0.6.5.dist-info/METADATA
backpipe-0.6.5.dist-info/WHEEL
backpipe-0.6.5.dist-info/entry_points.txt
backpipe-0.6.5.dist-info/top_level.txt
backpipe-0.6.5.dist-info/RECORD
