Metadata-Version: 2.1
Name: backpipe
Version: 0.6.5
Summary: A backend HTTP framework for Python.
Home-page: https://github.com/Simoso68/backpipe
Author: Simoso68
Maintainer: Simoso68
License: GNU GPL v3
Keywords: framework,http,web,api,server
Classifier: Development Status :: 4 - Beta
Classifier: Intended Audience :: Developers
Classifier: Topic :: Internet :: WWW/HTTP :: HTTP Servers
Classifier: License :: OSI Approved :: GNU General Public License v3 (GPLv3)
Classifier: Programming Language :: Python :: 3
Classifier: Natural Language :: English
Classifier: Environment :: Console
License-File: LICENSE
Requires-Dist: colorama
Requires-Dist: packaging
